dbn_cache/__init__.py
dbn_cache/cache.py
dbn_cache/calendar.py
dbn_cache/cli.py
dbn_cache/client.py
dbn_cache/exceptions.py
dbn_cache/futures.py
dbn_cache/models.py
dbn_cache/utils.py
dbn_cache-1.2.4.dist-info/METADATA
dbn_cache-1.2.4.dist-info/WHEEL
dbn_cache-1.2.4.dist-info/entry_points.txt
dbn_cache-1.2.4.dist-info/licenses/LICENSE
dbn_cache-1.2.4.dist-info/RECORD
