Metadata-Version: 2.4
Name: dbn-cache
Version: 1.2.4
Summary: Download and cache historical market data from Databento
Project-URL: Homepage, https://github.com/azizuysal/dbn-cache
Project-URL: Repository, https://github.com/azizuysal/dbn-cache
Project-URL: Issues, https://github.com/azizuysal/dbn-cache/issues
Author: Aziz Uysal
License-Expression: MIT
License-File: LICENSE
Keywords: backtesting,cache,databento,finance,market-data,trading
Classifier: Development Status :: 5 - Production/Stable
Classifier: Environment :: Console
Classifier: Intended Audience :: Developers
Classifier: Intended Audience :: Financial and Insurance Industry
Classifier: License :: OSI Approved :: MIT License
Classifier: Programming Language :: Python :: 3.13
Classifier: Topic :: Office/Business :: Financial :: Investment
Requires-Python: >=3.13
Requires-Dist: click>=8.0
Requires-Dist: databento>=0.40
Requires-Dist: exchange-calendars>=4.12
Requires-Dist: filelock>=3.0
Requires-Dist: pandas<3,>=2.0
Requires-Dist: polars>=1.0
Requires-Dist: pyarrow>=18.0
Requires-Dist: pydantic>=2.0
Requires-Dist: rich>=13.0
